deebee/__init__.py
deebee/db.py
deebee/postgresql.py
deebee-0.0.0.dist-info/LICENSE
deebee-0.0.0.dist-info/WHEEL
deebee-0.0.0.dist-info/METADATA
deebee-0.0.0.dist-info/RECORD
